typed_linq_collections/__init__.py
typed_linq_collections/py.typed
typed_linq_collections/q_cast.py
typed_linq_collections/q_errors.py
typed_linq_collections/q_grouping.py
typed_linq_collections/q_iterable.py
typed_linq_collections/q_ordered_iterable.py
typed_linq_collections/_private_implementation_details/__init__.py
typed_linq_collections/_private_implementation_details/immutable_sequence.py
typed_linq_collections/_private_implementation_details/q_lazy_iterable.py
typed_linq_collections/_private_implementation_details/q_zero_overhead_collection_contructors.py
typed_linq_collections/_private_implementation_details/sort_by_instructions.py
typed_linq_collections/_private_implementation_details/sort_instruction.py
typed_linq_collections/_private_implementation_details/type_aliases.py
typed_linq_collections/_private_implementation_details/ops/__init__.py
typed_linq_collections/_private_implementation_details/ops/aggregate.py
typed_linq_collections/_private_implementation_details/ops/all.py
typed_linq_collections/_private_implementation_details/ops/any.py
typed_linq_collections/_private_implementation_details/ops/append.py
typed_linq_collections/_private_implementation_details/ops/as_.py
typed_linq_collections/_private_implementation_details/ops/as_ints.py
typed_linq_collections/_private_implementation_details/ops/chunk.py
typed_linq_collections/_private_implementation_details/ops/concat.py
typed_linq_collections/_private_implementation_details/ops/contains.py
typed_linq_collections/_private_implementation_details/ops/distinct.py
typed_linq_collections/_private_implementation_details/ops/distinct_by.py
typed_linq_collections/_private_implementation_details/ops/element_at.py
typed_linq_collections/_private_implementation_details/ops/element_at_or_none.py
typed_linq_collections/_private_implementation_details/ops/first.py
typed_linq_collections/_private_implementation_details/ops/first_or_none.py
typed_linq_collections/_private_implementation_details/ops/group_by_q.py
typed_linq_collections-0.9.19.dist-info/licenses/LICENSE
typed_linq_collections-0.9.19.dist-info/METADATA
typed_linq_collections-0.9.19.dist-info/WHEEL
typed_linq_collections-0.9.19.dist-info/top_level.txt
typed_linq_collections-0.9.19.dist-info/RECORD
