Metadata-Version: 2.4
Name: typed-linq-collections
Version: 0.9.19
Summary: Complete LINQ, language integrated query, implementation for Python with full type annotations, comprehensive documentation, 100% test coverage, and queryable drop in replacements for the builtin collection types.
Author: Magnus Lidbom
License-Expression: MIT
Project-URL: Homepage, https://github.com/mlidbom/typed_linq_collections
Project-URL: Repository, https://github.com/mlidbom/typed_linq_collections
Project-URL: Issues, https://github.com/mlidbom/typed_linq_collections/issues
Classifier: Operating System :: OS Independent
Classifier: Topic :: Software Development :: Libraries :: Python Modules
Classifier: Typing :: Typed
Requires-Python: >=3.13
License-File: LICENSE
Dynamic: license-file
